commands/__init__.py
commands/exporter.py
commands/flusher.py
commands/migrator.py
metabasepy2/__init__.py
metabasepy2/client.py
metabasepy2/table_parser.py
metabasepy2-2.0.0.dist-info/LICENSE
metabasepy2-2.0.0.dist-info/METADATA
metabasepy2-2.0.0.dist-info/WHEEL
metabasepy2-2.0.0.dist-info/top_level.txt
metabasepy2-2.0.0.dist-info/RECORD
