Metadata-Version: 2.1
Name: metabasepy2
Version: 2.0.0
Summary: metabase api python client
Home-page: https://github.com/liadmo/metabasepy
Author: liadmo
Author-email: liad.mordekoviz@gmail.com
License: The MIT License (MIT)
